rusty_dawg-0.2.2.dist-info/METADATA
rusty_dawg-0.2.2.dist-info/WHEEL
rusty_dawg/__init__.py
rusty_dawg/rusty_dawg.cpython-310-aarch64-linux-gnu.so
rusty_dawg-0.2.2.dist-info/RECORD
