Metadata-Version: 2.3
Name: rusty-dawg
Version: 0.2.2
Summary: A Rust library for building and querying Directed Acyclic Word Graphs (DAWGs) and Compacted DAWGs (CDAWGs) for efficient string indexing and searching.
Author: lambdaviking
Requires-Python: >=3.10
